no_proxy.py
no_proxy-0.1.0.dist-info/licenses/LICENSE
no_proxy-0.1.0.dist-info/METADATA
no_proxy-0.1.0.dist-info/WHEEL
no_proxy-0.1.0.dist-info/top_level.txt
no_proxy-0.1.0.dist-info/RECORD
