Metadata-Version: 2.4
Name: no-proxy
Version: 0.1.0
Summary: Add your description here
Author-email: Pascal Bachor <no-proxy.overtone042@passinbox.com>
Maintainer-email: Pascal Bachor <no-proxy.overtone042@passinbox.com>
License-Expression: MIT
Project-URL: source, https://github.com/bachorp/no-proxy
Project-URL: changelog, https://github.com/bachorp/no-proxy/blob/HEAD/CHANGELOG.md
Project-URL: documentation, https://github.com/bachorp/no-proxy/#no-proxy
Project-URL: issues, https://github.com/bachorp/no-proxy/issues
Keywords: proxy,no_proxy,NO_PROXY
Requires-Python: >=3.9
License-File: LICENSE
Dynamic: license-file
